basic_pip_abhi/__init__.py
basic_pip_abhi/calculate.py
basic_pip_abhi-0.0.1.dist-info/METADATA
basic_pip_abhi-0.0.1.dist-info/WHEEL
basic_pip_abhi-0.0.1.dist-info/top_level.txt
basic_pip_abhi-0.0.1.dist-info/RECORD
