Metadata-Version: 2.1
Name: basic-pip-abhi
Version: 0.0.1
Summary: first pip package
Author: Abhijeet jadhav
Author-email: abhisinh128@gmail.com
Classifier: Programming Language :: Python :: 3
Classifier: License :: OSI Approved :: MIT License
Classifier: Operating System :: OS Independent
Requires-Python: >=3.7
